{
  "result": "success",
  "errmsg": null,
  "data": {
    "topoTitle": "",
    "scene": {
      "elementType": "scene",
      "id": -1,
      "translateX": -280.42,
      "translateY": -132.92,
      "scaleX": 0.71,
      "scaleY": 0.71,
      "childs": [
        {
          "id": 0,
          "elementType": "node",
          "devId": 4,
          "devIp": "1.1.1.1",
          "devLabel": "设备一",
          "devType": 2,
          "status": 1,
          "x": 1005.72,
          "y": 364.71,
          "fullx": 358.95,
          "fully": 452.11,
          "width": 34.0,
          "height": 24.0,
          "visible": true,
          "rotate": 0.0,
          "scaleX": 1.0,
          "scaleY": 1.0,
          "zIndex": 3,
          "nodeId": "24580c49-7129-4b37-bc3b-92af3caa04d8",
          "nodeType": "dev",
          "nodeParams": "",
          "nodeImage": "a.png",
          "text": "设备1(1.1.1.1)",
          "textPosition": "Bottom_Center",
          "layout": "",
          "scene": -1,
          "alarm": null,
          "alarmColor": "",
          "alarmAlpha": 0.5
        },
        {
          "id": 0,
          "elementType": "node",
          "devId": 1,
          "devIp": "10.1.1.4",
          "devLabel": "设备二",
          "devType": 2,
          "status": 1,
          "x": 666.2,
          "y": 239.89,
          "fullx": 52.16,
          "fully": 462.52,
          "width": 34.0,
          "height": 24.0,
          "visible": true,
          "rotate": 0.0,
          "scaleX": 1.0,
          "scaleY": 1.0,
          "zIndex": 3,
          "nodeId": "e95d5c78-7f1e-46a7-a7e5-3339bdb53252",
          "nodeType": "dev",
          "nodeParams": "",
          "nodeImage": "b.png",
          "text": "设备2(10.1.1.4)",
          "textPosition": "Bottom_Center",
          "layout": "",
          "scene": -1,
          "alarm": null,
          "alarmColor": "",
          "alarmAlpha": 0.5
        },
        {
          "id": "b8a5a09f-7547-490d-941f-d7273f9ba649",
          "elementType": "link",
          "x": 0.0,
          "y": 0.0,
          "width": 32,
          "height": 32,
          "visible": true,
          "rotate": 0,
          "scaleX": 1,
          "scaleY": 1,
          "zIndex": 2,
          "localDevId": 3,
          "localDevIp": "10.1.4.17",
          "localDevIfindex": 805306368,
          "localDevIfname": "",
          "remoteDevId": 5,
          "remoteDevIp": "10.1.4.254",
          "remoteDevIfindex": 100663307,
          "remoteDevIfname": "",
          "nodeSrc": "24580c49-7129-4b37-bc3b-92af3caa04d8",
          "nodeDst": "e95d5c78-7f1e-46a7-a7e5-3339bdb53252",
          "lineType": "line",
          "direction": "",
          "text": "",
          "linkParams": "",
          "lineClass": "dev",
          "status": 0,
          "strokeColor": "18,150,219",
          "scene": -1
        }
      ]
    },
    "autoLayout": false
  }
}
